pystartgg/__init__.py
pystartgg/api.py
pystartgg/b_queries.py
pystartgg/brackets.py
pystartgg/e_queries.py
pystartgg/events.py
pystartgg/exceptions.py
pystartgg/l_queries.py
pystartgg/leagues.py
pystartgg/p_queries.py
pystartgg/players.py
pystartgg/pystartgg.py
pystartgg/t_queries.py
pystartgg/tournaments.py
pystartgg-0.0.16.dist-info/METADATA
pystartgg-0.0.16.dist-info/WHEEL
pystartgg-0.0.16.dist-info/RECORD
