Metadata-Version: 2.3
Name: pystartgg
Version: 0.0.16
Summary: Python wrapper for startgg API calls.
License: MIT
Author: Steven
Author-email: shepsteven42@gmail.com
Requires-Python: >=3.12
Classifier: License :: OSI Approved :: MIT License
Classifier: Programming Language :: Python :: 3
Classifier: Programming Language :: Python :: 3.12
Classifier: Programming Language :: Python :: 3.13
Requires-Dist: requests
